{
  "componentName": "Collection",
  "actionCodeGroupName": "Collectable Event",
  "apiName": "Fetch Collectable Event",
  "parameterList": [
    "column1"
  ],
  "resultColumnMap": {
    "column1": {
      "technicalColumnName": "column1",
      "isMandatory": true,
      "derivedDataType": "String(20)"
    },
    "column2": {
      "technicalColumnName": "column2",
      "isMandatory": true,
      "derivedDataType": "String(20)"
    },
    "column3": {
      "technicalColumnName": "column3",
      "isMandatory": true,
      "derivedDataType": "String(20)"
    }
  }
}